ovos_workshop/__init__.py
ovos_workshop/app.py
ovos_workshop/backwards_compat.py
ovos_workshop/filesystem.py
ovos_workshop/intents.py
ovos_workshop/permissions.py
ovos_workshop/resource_files.py
ovos_workshop/settings.py
ovos_workshop/skill_launcher.py
ovos_workshop/version.py
ovos_workshop/decorators/__init__.py
ovos_workshop/decorators/fallback_handler.py
ovos_workshop/decorators/killable.py
ovos_workshop/decorators/layers.py
ovos_workshop/decorators/ocp.py
ovos_workshop/locale/az/word_connectors.json
ovos_workshop/locale/ca/word_connectors.json
ovos_workshop/locale/cs/noise_words.list
ovos_workshop/locale/cs/word_connectors.json
ovos_workshop/locale/da/word_connectors.json
ovos_workshop/locale/de/noise_words.list
ovos_workshop/locale/de/word_connectors.json
ovos_workshop/locale/en/cancel.voc
ovos_workshop/locale/en/cant_load_game.dialog
ovos_workshop/locale/en/cant_save_game.dialog
ovos_workshop/locale/en/game_pause.dialog
ovos_workshop/locale/en/game_unpause.dialog
ovos_workshop/locale/en/noise_words.list
ovos_workshop/locale/en/skill.error.dialog
ovos_workshop/locale/en/word_connectors.json
ovos_workshop/locale/es/word_connectors.json
ovos_workshop/locale/fa/word_connectors.json
ovos_workshop/locale/gl/word_connectors.json
ovos_workshop/locale/it/word_connectors.json
ovos_workshop/locale/nl/skill.error.dialog
ovos_workshop/locale/nl/word_connectors.json
ovos_workshop/locale/pl/word_connectors.json
ovos_workshop/locale/pt/word_connectors.json
ovos_workshop/locale/ru/noise_words.list
ovos_workshop/locale/sl/word_connectors.json
ovos_workshop/locale/uk/word_connectors.json
ovos_workshop/skills/__init__.py
ovos_workshop/skills/active.py
ovos_workshop/skills/api.py
ovos_workshop/skills/auto_translatable.py
ovos_workshop/skills/common_play.py
ovos_workshop/skills/common_query_skill.py
ovos_workshop/skills/converse.py
ovos_workshop/skills/fallback.py
ovos_workshop/skills/game_skill.py
ovos_workshop/skills/idle_display_skill.py
ovos_workshop/skills/intent_provider.py
ovos_workshop-8.0.0.dist-info/licenses/LICENSE
ovos_workshop-8.0.0.dist-info/METADATA
ovos_workshop-8.0.0.dist-info/WHEEL
ovos_workshop-8.0.0.dist-info/entry_points.txt
ovos_workshop-8.0.0.dist-info/top_level.txt
ovos_workshop-8.0.0.dist-info/RECORD
