Metadata-Version: 2.4
Name: ovos_workshop
Version: 8.0.0
Summary: frameworks, templates and patches for the OpenVoiceOS universe
Home-page: https://github.com/OpenVoiceOS/OVOS-workshop
Author: jarbasAi
Author-email: jarbasai@mailfence.com
License: apache-2.0
License-File: LICENSE
Requires-Dist: ovos-utils<1.0.0,>=0.7.0
Requires-Dist: ovos_bus_client<2.0.0,>=1.3.8a1
Requires-Dist: ovos-config<3.0.0,>=0.0.12
Requires-Dist: ovos-solver-yes-no-plugin<1.0.0,>=0.0.1
Requires-Dist: ovos-number-parser<1.0.0,>=0.0.1
Requires-Dist: rapidfuzz
Requires-Dist: langcodes
Requires-Dist: padacioso<2.0.0,>=1.0.0
Dynamic: author
Dynamic: author-email
Dynamic: description
Dynamic: description-content-type
Dynamic: home-page
Dynamic: license
Dynamic: license-file
Dynamic: requires-dist
Dynamic: summary
